teek/__init__.py
teek/_font.py
teek/_platform_info.py
teek/_structures.py
teek/_tcl_calls.py
teek/_timeouts.py
teek/dialog.py
teek/_widgets/__init__.py
teek/_widgets/base.py
teek/_widgets/canvas.py
teek/_widgets/menu.py
teek/_widgets/misc.py
teek/_widgets/notebook.py
teek/_widgets/text.py
teek/_widgets/windows.py
teek/extras/__init__.py
teek/extras/cross_platform.py
teek/extras/image_loader.py
teek/extras/image_loader_dummy.py
teek/extras/links.py
teek/extras/more_dialogs.py
teek/extras/soup.py
teek/extras/tooltips.py
teek-0.6.dist-info/LICENSE
teek-0.6.dist-info/WHEEL
teek-0.6.dist-info/METADATA
teek-0.6.dist-info/RECORD
