Metadata-Version: 2.1
Name: teek
Version: 0.6
Summary: Teek is a pythonic alternative to tkinter.
Home-page: https://github.com/Akuli/teek
License: UNKNOWN
Keywords: pythonic tk tcl tkinter gui beginner
Author: Akuli
Author-email: akuviljanen17@gmail.com
Requires-Python: >=3.5
Requires-Dist: pillow ; extra == "image_loader"
Requires-Dist: reportlab ; extra == "image_loader"
Requires-Dist: svglib==0.9.0 ; extra == "image_loader"
Requires-Dist: lxml ; extra == "image_loader"
Requires-Dist: beautifulsoup4 ; extra == "soup_viewer"
Requires-Dist: lxml ; extra == "soup_viewer"
Provides-Extra: image_loader
Provides-Extra: soup_viewer
